glide_data_synthesis/__init__.py
glide_data_synthesis/metrics.py
glide_data_synthesis/models.py
glide_data_synthesis/programs/__init__.py
glide_data_synthesis/programs/incident_table.py
glide_data_synthesis-0.1.dist-info/METADATA
glide_data_synthesis-0.1.dist-info/WHEEL
glide_data_synthesis-0.1.dist-info/top_level.txt
glide_data_synthesis-0.1.dist-info/RECORD
